fourier_accountant/__init__.py
fourier_accountant/common.py
fourier_accountant/compute_delta.py
fourier_accountant/compute_delta_var.py
fourier_accountant/compute_eps.py
fourier_accountant/compute_eps_var.py
pld_accountant-0.12.1.dist-info/LICENSE
pld_accountant-0.12.1.dist-info/METADATA
pld_accountant-0.12.1.dist-info/WHEEL
pld_accountant-0.12.1.dist-info/top_level.txt
pld_accountant-0.12.1.dist-info/RECORD
