Metadata-Version: 2.1
Name: pld-accountant
Version: 0.12.1
Summary: Fourier Accountant for Differential Privacy 
Home-page: https://github.com/DPBayes/PLD-Accountant
Author: Antti Koskela
Author-email: anttik123@gmail.com
License: UNKNOWN
Platform: UNKNOWN
Classifier: Intended Audience :: Science/Research
Classifier: Programming Language :: Python :: 3
Classifier: License :: OSI Approved :: MIT License
Classifier: Operating System :: OS Independent
Requires-Dist: numpy
